time_tools/__init__.py
time_tools/customTimer.py
time_tools/stopwatch.py
time_tools/ticker.py
time_tools-1.0.0.dist-info/DESCRIPTION.rst
time_tools-1.0.0.dist-info/METADATA
time_tools-1.0.0.dist-info/RECORD
time_tools-1.0.0.dist-info/WHEEL
time_tools-1.0.0.dist-info/metadata.json
time_tools-1.0.0.dist-info/top_level.txt
